[{"id":109377,"name":"Berestechko","latitude":50.36047,"longitude":25.11071},{"id":109409,"name":"Blahodatne","latitude":50.66365,"longitude":24.24918},{"id":109656,"name":"Hołoby","latitude":51.08651,"longitude":25.00767},{"id":109653,"name":"Horokhiv","latitude":50.50186,"longitude":24.76149},{"id":109712,"name":"Kamin-Kashyrskyi","latitude":51.62412,"longitude":24.95864},{"id":109756,"name":"Kivertsi","latitude":50.83425,"longitude":25.45821},{"id":109820,"name":"Kovel","latitude":51.21526,"longitude":24.70867},{"id":109821,"name":"Kovel’s’ka Mis’krada","latitude":51.21198,"longitude":24.70163},{"id":109924,"name":"Liuboml","latitude":51.22601,"longitude":24.03727},{"id":109928,"name":"Lokachi","latitude":50.737,"longitude":24.64944},{"id":109943,"name":"Lukiv","latitude":51.0521,"longitude":25.40059},{"id":109944,"name":"Lutsk","latitude":50.75932,"longitude":25.34244},{"id":109964,"name":"Lyubeshivs’kyy Rayon","latitude":51.79639,"longitude":25.33133},{"id":109965,"name":"Lyuboml’s’kyy Rayon","latitude":51.25062,"longitude":24.01161},{"id":109992,"name":"Manevychi","latitude":51.29405,"longitude":25.53436},{"id":109993,"name":"Manevyts’kyy Rayon","latitude":51.24513,"longitude":25.60945},{"id":110152,"name":"Novovolyns’k","latitude":50.72576,"longitude":24.16265},{"id":110162,"name":"Nuyno","latitude":51.54628,"longitude":24.91018},{"id":110195,"name":"Olyka","latitude":50.71855,"longitude":25.81251},{"id":110273,"name":"Pishcha","latitude":51.60928,"longitude":23.82079},{"id":110342,"name":"Rakiv Lis","latitude":51.62174,"longitude":24.92427},{"id":110345,"name":"Ratne","latitude":51.6683,"longitude":24.5303},{"id":110346,"name":"Ratnivs’kyy Rayon","latitude":51.71712,"longitude":24.51959},{"id":110381,"name":"Rozhyshche","latitude":50.91542,"longitude":25.26906},{"id":110431,"name":"Shats’k","latitude":51.50208,"longitude":23.93806},{"id":110432,"name":"Shats’kyy Rayon","latitude":51.52237,"longitude":23.86522},{"id":110528,"name":"Stara Vyzhivka","latitude":51.43762,"longitude":24.43997},{"id":110578,"name":"Svityaz’","latitude":51.48211,"longitude":23.85904},{"id":110734,"name":"Volodymyr-Volynskyi","latitude":50.85253,"longitude":24.32364}]