[{"id":129904,"name":"Beshkent","latitude":38.82139,"longitude":65.65306},{"id":129916,"name":"Chiroqchi","latitude":39.03361,"longitude":66.57222},{"id":129931,"name":"G‘uzor","latitude":38.62083,"longitude":66.24806},{"id":129949,"name":"Kitob","latitude":39.08425,"longitude":66.83318},{"id":129951,"name":"Koson","latitude":39.0375,"longitude":65.585},{"id":129958,"name":"Muborak","latitude":39.25528,"longitude":65.15278},{"id":129962,"name":"Nishon Tumani","latitude":38.69395,"longitude":65.67512},{"id":129981,"name":"Qarshi","latitude":38.86056,"longitude":65.78905},{"id":129997,"name":"Shahrisabz","latitude":39.05778,"longitude":66.83417}]