[{"id":53839,"name":"Agua Caliente","latitude":14.88333,"longitude":-88.81667},{"id":53876,"name":"Buenos Aires","latitude":15.03333,"longitude":-88.96667},{"id":53878,"name":"Cabañas","latitude":14.76,"longitude":-89.06},{"id":53896,"name":"Chalmeca","latitude":15.1,"longitude":-88.68333},{"id":53911,"name":"Concepción","latitude":14.88077,"longitude":-88.87919},{"id":53914,"name":"Concepción de la Barranca","latitude":15.16667,"longitude":-88.71667},{"id":53918,"name":"Copán","latitude":14.83333,"longitude":-89.15},{"id":53919,"name":"Copán Ruinas","latitude":14.92,"longitude":-89.15},{"id":53923,"name":"Corquín","latitude":14.56667,"longitude":-88.86667},{"id":53927,"name":"Cucuyagua","latitude":14.65,"longitude":-88.86667},{"id":53934,"name":"Dolores","latitude":14.86667,"longitude":-88.83333},{"id":53937,"name":"Dulce Nombre","latitude":14.85552,"longitude":-88.83856},{"id":53948,"name":"El Corpus","latitude":14.7,"longitude":-88.91667},{"id":53968,"name":"El Ocotón","latitude":15.03333,"longitude":-88.88333},{"id":53971,"name":"El Paraíso","latitude":15.04217,"longitude":-88.98045},{"id":54005,"name":"Florida","latitude":15.03333,"longitude":-88.83333},{"id":54052,"name":"La Entrada","latitude":15.05,"longitude":-88.73333},{"id":54064,"name":"La Jigua","latitude":15.1,"longitude":-88.76},{"id":54074,"name":"La Playona","latitude":15.11667,"longitude":-88.98333},{"id":54083,"name":"La Unión","latitude":14.6935,"longitude":-88.94734},{"id":54086,"name":"La Zumbadora","latitude":15.01667,"longitude":-88.9},{"id":54111,"name":"Los Tangos","latitude":15.15,"longitude":-88.68333},{"id":54144,"name":"Nueva Arcadia","latitude":15.08,"longitude":-88.69},{"id":54156,"name":"Ojos de Agua","latitude":14.7,"longitude":-88.81667},{"id":54181,"name":"Pueblo Nuevo","latitude":15.0,"longitude":-88.75},{"id":54194,"name":"Quezailica","latitude":14.88333,"longitude":-88.73333},{"id":54209,"name":"San Agustín","latitude":14.81973,"longitude":-88.93027},{"id":54214,"name":"San Antonio","latitude":15.04,"longitude":-88.88},{"id":54241,"name":"San Jerónimo","latitude":14.96207,"longitude":-88.9027},{"id":54242,"name":"San Joaquín","latitude":15.05,"longitude":-88.9},{"id":54245,"name":"San José","latitude":14.91184,"longitude":-88.71667},{"id":54250,"name":"San José de Copán","latitude":14.9,"longitude":-88.71667},{"id":54261,"name":"San Juan de Opoa","latitude":14.78333,"longitude":-88.7},{"id":54262,"name":"San Juan de Planes","latitude":14.93333,"longitude":-88.78333},{"id":54279,"name":"San Nicolás","latitude":14.98,"longitude":-88.73},{"id":54283,"name":"San Pedro de Copán","latitude":14.61667,"longitude":-88.8},{"id":54310,"name":"Santa Rita","latitude":14.88,"longitude":-89.01},{"id":54311,"name":"Santa Rita Copan","latitude":14.86748,"longitude":-89.1},{"id":54313,"name":"Santa Rosa de Copán","latitude":14.76667,"longitude":-88.77917},{"id":54346,"name":"Trinidad de Copán","latitude":14.95,"longitude":-88.75},{"id":54357,"name":"Veracruz","latitude":14.88343,"longitude":-88.7857}]