[{"id":89871,"name":"1 Decembrie","latitude":44.29083,"longitude":26.05806},{"id":89891,"name":"Afumaţi","latitude":44.51667,"longitude":26.26667},{"id":89943,"name":"Alunișu","latitude":44.33883,"longitude":26.05837},{"id":90521,"name":"Bălăceanca","latitude":44.39249,"longitude":26.29009},{"id":90045,"name":"Baloteşti","latitude":44.61667,"longitude":26.11667},{"id":90099,"name":"Berceni","latitude":44.31417,"longitude":26.18556},{"id":90264,"name":"Bragadiru","latitude":44.37111,"longitude":25.9775},{"id":90337,"name":"Brăneşti","latitude":44.45,"longitude":26.33333},{"id":90352,"name":"Buciumeni","latitude":44.54975,"longitude":25.96419},{"id":90391,"name":"Buftea","latitude":44.56139,"longitude":25.94889},{"id":90416,"name":"Buriaș","latitude":44.73304,"longitude":25.98053},{"id":93824,"name":"Căciulați","latitude":44.62741,"longitude":26.17255},{"id":93833,"name":"Căldăraru","latitude":44.41307,"longitude":26.26313},{"id":93886,"name":"Cățelu","latitude":44.40292,"longitude":26.21975},{"id":90635,"name":"Cernica","latitude":44.41667,"longitude":26.28333},{"id":90662,"name":"Chiajna","latitude":44.46,"longitude":25.97333},{"id":90684,"name":"Chitila","latitude":44.50806,"longitude":25.98222},{"id":90717,"name":"Ciofliceni","latitude":44.68122,"longitude":26.11923},{"id":90720,"name":"Ciolpani","latitude":44.73333,"longitude":26.08333},{"id":90726,"name":"Ciorogârla","latitude":44.4425,"longitude":25.88333},{"id":90767,"name":"Clinceni","latitude":44.37333,"longitude":25.95472},{"id":90816,"name":"Comuna 1 Decembrie","latitude":44.28869,"longitude":26.06178},{"id":90828,"name":"Comuna Afumaţi","latitude":44.52501,"longitude":26.24943},{"id":90927,"name":"Comuna Baloteşti","latitude":44.62026,"longitude":26.08664},{"id":90961,"name":"Comuna Berceni","latitude":44.30887,"longitude":26.19051},{"id":91123,"name":"Comuna Brăneşti","latitude":44.45362,"longitude":26.34995},{"id":91293,"name":"Comuna Cernica","latitude":44.39343,"longitude":26.28992},{"id":91311,"name":"Comuna Chiajna","latitude":44.45499,"longitude":25.99345},{"id":91350,"name":"Comuna Ciolpani","latitude":44.72603,"longitude":26.10193},{"id":91354,"name":"Comuna Ciorogârla","latitude":44.43222,"longitude":25.87861},{"id":91381,"name":"Comuna Clinceni","latitude":44.37639,"longitude":25.92445},{"id":91420,"name":"Comuna Copăceni","latitude":44.26297,"longitude":26.09374},{"id":91423,"name":"Comuna Corbeanca","latitude":44.59671,"longitude":26.03241},{"id":91437,"name":"Comuna Cornetu","latitude":44.34286,"longitude":25.92489},{"id":91746,"name":"Comuna Dărăşti-Ilfov","latitude":44.30912,"longitude":26.02139},{"id":91605,"name":"Comuna Dascălu Creaţa","latitude":44.60008,"longitude":26.24201},{"id":91658,"name":"Comuna Domneşti","latitude":44.39058,"longitude":25.89492},{"id":91675,"name":"Comuna Dragomireşti-Vale","latitude":44.47555,"longitude":25.93164},{"id":91801,"name":"Comuna Fundeni-Dobroeşti","latitude":44.45455,"longitude":26.18368},{"id":91985,"name":"Comuna Găneasa","latitude":44.49447,"longitude":26.29923},{"id":91880,"name":"Comuna Glina","latitude":44.38546,"longitude":26.24582},{"id":91938,"name":"Comuna Grădiştea","latitude":44.66557,"longitude":26.31448},{"id":91931,"name":"Comuna Gruiu","latitude":44.72648,"longitude":26.22133},{"id":92123,"name":"Comuna Jilava","latitude":44.32863,"longitude":26.07754},{"id":92313,"name":"Comuna Moara Vlãsiei","latitude":44.63416,"longitude":26.18935},{"id":92321,"name":"Comuna Mogoşoaia","latitude":44.52903,"longitude":26.00178},{"id":92455,"name":"Comuna Nuci","latitude":44.7091,"longitude":26.3177},{"id":92553,"name":"Comuna Periş","latitude":44.70859,"longitude":26.01472},{"id":92569,"name":"Comuna Petrăchioaia","latitude":44.57953,"longitude":26.31114},{"id":92967,"name":"Comuna Snagov","latitude":44.68481,"longitude":26.12384},{"id":93554,"name":"Comuna Ştefãneştii De Jos","latitude":44.53333,"longitude":26.18333},{"id":93207,"name":"Comuna Tunari","latitude":44.56797,"longitude":26.13908},{"id":93355,"name":"Comuna Vidra","latitude":44.28107,"longitude":26.1431},{"id":93607,"name":"Copăceni","latitude":44.26297,"longitude":26.09374},{"id":93612,"name":"Corbeanca","latitude":44.6,"longitude":26.05},{"id":93633,"name":"Cornetu","latitude":44.34167,"longitude":25.94083},{"id":93714,"name":"Crețești","latitude":44.28238,"longitude":26.1353},{"id":94134,"name":"Dărăşti-Ilfov","latitude":44.30889,"longitude":26.01833},{"id":94112,"name":"Dârvari","latitude":44.42108,"longitude":25.87989},{"id":93897,"name":"Dascălu","latitude":44.6,"longitude":26.23333},{"id":93961,"name":"Dobroeşti","latitude":44.45,"longitude":26.18333},{"id":93991,"name":"Domnești","latitude":44.39919,"longitude":25.91618},{"id":93990,"name":"Domneşti-Sârbi","latitude":44.38333,"longitude":25.91667},{"id":94020,"name":"Dragomirești-Deal","latitude":44.4624,"longitude":25.94478},{"id":94019,"name":"Dragomireşti-Vale","latitude":44.475,"longitude":25.935},{"id":94226,"name":"Fundeni","latitude":44.45892,"longitude":26.16565},{"id":94510,"name":"Găneasa","latitude":44.48333,"longitude":26.28333},{"id":94309,"name":"Ghermănești","latitude":44.68829,"longitude":26.14962},{"id":94358,"name":"Glina","latitude":44.38333,"longitude":26.25},{"id":94438,"name":"Grădiştea","latitude":44.66667,"longitude":26.28333},{"id":94430,"name":"Gruiu","latitude":44.73333,"longitude":26.23333},{"id":94690,"name":"Islaz","latitude":44.46117,"longitude":26.38724},{"id":94736,"name":"Jilava","latitude":44.33333,"longitude":26.07806},{"id":94800,"name":"Lipia","latitude":44.71003,"longitude":26.26445},{"id":95243,"name":"Măgurele","latitude":44.35,"longitude":26.03333},{"id":94958,"name":"Merii Petchii","latitude":44.73532,"longitude":26.30054},{"id":95043,"name":"Moara Vlăsiei","latitude":44.6409,"longitude":26.20616},{"id":95055,"name":"Mogoşoaia","latitude":44.52917,"longitude":26.0},{"id":95361,"name":"Nuci","latitude":44.71667,"longitude":26.3},{"id":95431,"name":"Olteni","latitude":44.39307,"longitude":25.95021},{"id":95469,"name":"Oraş Bragadiru","latitude":44.36998,"longitude":25.97871},{"id":95475,"name":"Oraş Buftea","latitude":44.55475,"longitude":25.95628},{"id":95491,"name":"Oraş Chitila","latitude":44.49053,"longitude":25.97847},{"id":95546,"name":"Oraş Mãgurele","latitude":44.33925,"longitude":26.01403},{"id":95561,"name":"Oraş Otopeni","latitude":44.54217,"longitude":26.06526},{"id":95565,"name":"Oraş Pantelimon","latitude":44.45235,"longitude":26.20684},{"id":95571,"name":"Oraş Popeşti Leordeni","latitude":44.38005,"longitude":26.17134},{"id":95684,"name":"Otopeni","latitude":44.55,"longitude":26.06667},{"id":95706,"name":"Pantelimon","latitude":44.45,"longitude":26.2},{"id":95735,"name":"Periş","latitude":44.68472,"longitude":26.01389},{"id":95758,"name":"Petrăchioaia","latitude":44.58099,"longitude":26.31269},{"id":95802,"name":"Piteasca","latitude":44.49339,"longitude":26.33025},{"id":95912,"name":"Popeşti-Leordeni","latitude":44.38333,"longitude":26.16667},{"id":96142,"name":"Roșu","latitude":44.45025,"longitude":26.01122},{"id":96146,"name":"Rudeni","latitude":44.47242,"longitude":25.97325},{"id":96345,"name":"Siliștea Snagovului","latitude":44.7392,"longitude":26.17942},{"id":96357,"name":"Sintești","latitude":44.30046,"longitude":26.12126},{"id":96393,"name":"Snagov","latitude":44.7,"longitude":26.18333},{"id":97087,"name":"Ştefăneştii de Jos","latitude":44.53333,"longitude":26.2},{"id":106056,"name":"Tamași","latitude":44.58438,"longitude":26.00724},{"id":96578,"name":"Tânganu","latitude":44.40628,"longitude":26.31262},{"id":96548,"name":"Tunari","latitude":44.55,"longitude":26.15},{"id":96943,"name":"Vârteju","latitude":44.35606,"longitude":25.99183},{"id":96809,"name":"Vidra","latitude":44.26056,"longitude":26.16972},{"id":96889,"name":"Voluntari","latitude":44.49002,"longitude":26.17338},{"id":96890,"name":"Voluntari City","latitude":44.49023,"longitude":26.18439}]