[{"id":85329,"name":"Abbottabad","latitude":34.1463,"longitude":73.21168},{"id":85333,"name":"Akora","latitude":34.00337,"longitude":72.12561},{"id":85337,"name":"Aman Garh","latitude":34.00584,"longitude":71.92971},{"id":85338,"name":"Amirabad","latitude":34.18729,"longitude":73.09078},{"id":85340,"name":"Ashanagro Koto","latitude":34.10773,"longitude":72.24517},{"id":85345,"name":"Baffa","latitude":34.4377,"longitude":73.22368},{"id":85351,"name":"Bannu","latitude":32.98527,"longitude":70.60403},{"id":85356,"name":"Bat Khela","latitude":34.6178,"longitude":71.97247},{"id":85357,"name":"Battagram","latitude":34.67719,"longitude":73.02329},{"id":85358,"name":"Battagram District","latitude":34.68051,"longitude":73.00535},{"id":85374,"name":"Buner District","latitude":34.44301,"longitude":72.49933},{"id":85387,"name":"Charsadda","latitude":34.14822,"longitude":71.7406},{"id":85390,"name":"Cherat Cantonement","latitude":33.82342,"longitude":71.89292},{"id":85395,"name":"Chitral","latitude":35.8518,"longitude":71.78636},{"id":85419,"name":"Dera Ismail Khan","latitude":31.83129,"longitude":70.9017},{"id":85420,"name":"Dera Ismāīl Khān District","latitude":31.85963,"longitude":70.64879},{"id":85430,"name":"Doaba","latitude":33.4245,"longitude":70.73676},{"id":85463,"name":"Hangu","latitude":33.53198,"longitude":71.0595},{"id":85464,"name":"Haripur","latitude":33.99783,"longitude":72.93493},{"id":85470,"name":"Havelian","latitude":34.05348,"longitude":73.15993},{"id":85504,"name":"Kakad Wari Dir Upper","latitude":34.99798,"longitude":72.07295},{"id":85522,"name":"Karak","latitude":33.11633,"longitude":71.09354},{"id":85536,"name":"Khalabat","latitude":34.05997,"longitude":72.88963},{"id":85551,"name":"Kohat","latitude":33.58196,"longitude":71.44929},{"id":85566,"name":"Kulachi","latitude":31.93058,"longitude":70.45959},{"id":85570,"name":"Lachi","latitude":33.38291,"longitude":71.33733},{"id":85574,"name":"Lakki","latitude":32.60724,"longitude":70.91234},{"id":85597,"name":"Mansehra","latitude":34.33023,"longitude":73.19679},{"id":85598,"name":"Mardan","latitude":34.19794,"longitude":72.04965},{"id":85610,"name":"Mingora","latitude":34.7795,"longitude":72.36265},{"id":85644,"name":"Noorabad","latitude":34.25195,"longitude":71.96656},{"id":85646,"name":"Nowshera","latitude":34.01583,"longitude":71.98123},{"id":85647,"name":"Nowshera Cantonment","latitude":33.99829,"longitude":71.99834},{"id":85652,"name":"Pabbi","latitude":34.00968,"longitude":71.79445},{"id":85654,"name":"Paharpur","latitude":32.10502,"longitude":70.97055},{"id":85661,"name":"Peshawar","latitude":34.008,"longitude":71.57849},{"id":85686,"name":"Risalpur Cantonment","latitude":34.06048,"longitude":71.99276},{"id":85700,"name":"Sarai Naurang","latitude":32.82581,"longitude":70.78107},{"id":85705,"name":"Shabqadar","latitude":34.21599,"longitude":71.5548},{"id":85716,"name":"Shingli Bala","latitude":34.67872,"longitude":72.98491},{"id":85718,"name":"Shorkot","latitude":31.91023,"longitude":70.87757},{"id":85733,"name":"Swabi","latitude":34.12018,"longitude":72.46982},{"id":85745,"name":"Tangi","latitude":34.3009,"longitude":71.65238},{"id":85747,"name":"Tank","latitude":32.21707,"longitude":70.38315},{"id":85749,"name":"Thal","latitude":35.47836,"longitude":72.24383},{"id":85754,"name":"Topi","latitude":34.07034,"longitude":72.62147},{"id":85759,"name":"Upper Dir","latitude":35.2074,"longitude":71.8768},{"id":85762,"name":"Utmanzai","latitude":34.18775,"longitude":71.76274},{"id":85770,"name":"Zaida","latitude":34.0595,"longitude":72.4669}]