[{"id":1950,"name":"Johor","state_code":"01"},{"id":1947,"name":"Kedah","state_code":"02"},{"id":1946,"name":"Kelantan","state_code":"03"},{"id":1949,"name":"Kuala Lumpur","state_code":"14"},{"id":1935,"name":"Labuan","state_code":"15"},{"id":1941,"name":"Malacca","state_code":"04"},{"id":1948,"name":"Negeri Sembilan","state_code":"05"},{"id":1940,"name":"Pahang","state_code":"06"},{"id":1939,"name":"Penang","state_code":"07"},{"id":1943,"name":"Perak","state_code":"08"},{"id":1938,"name":"Perlis","state_code":"09"},{"id":1945,"name":"Putrajaya","state_code":"16"},{"id":1936,"name":"Sabah","state_code":"12"},{"id":1937,"name":"Sarawak","state_code":"13"},{"id":1944,"name":"Selangor","state_code":"10"},{"id":1942,"name":"Terengganu","state_code":"11"}]